xml_augmenter/__init__.py
xml_augmenter/visualizer.py
xml_augmenter-0.1.0.dist-info/LICENSE
xml_augmenter-0.1.0.dist-info/METADATA
xml_augmenter-0.1.0.dist-info/WHEEL
xml_augmenter-0.1.0.dist-info/top_level.txt
xml_augmenter-0.1.0.dist-info/RECORD
