Metadata-Version: 2.1
Name: xml_augmenter
Version: 0.1.0
Summary: Simple XML file augmentation handler for segmentation based CV tasks
Author: nastics
License-File: LICENSE
Requires-Dist: numpy ==2.0.0
Requires-Dist: opencv-python ==4.10.0.84
